mne/__init__.py
mne/__init__.pyi
mne/__main__.py
mne/_freesurfer.py
mne/_ola.py
mne/_version.py
mne/annotations.py
mne/baseline.py
mne/bem.py
mne/chpi.py
mne/conftest.py
mne/coreg.py
mne/cov.py
mne/cuda.py
mne/defaults.py
mne/dipole.py
mne/epochs.py
mne/event.py
mne/evoked.py
mne/filter.py
mne/fixes.py
mne/label.py
mne/misc.py
mne/morph.py
mne/morph_map.py
mne/parallel.py
mne/proj.py
mne/rank.py
mne/source_estimate.py
mne/surface.py
mne/transforms.py
mne/_fiff/__init__.py
mne/_fiff/_digitization.py
mne/_fiff/compensator.py
mne/_fiff/constants.py
mne/_fiff/ctf_comp.py
mne/_fiff/matrix.py
mne/_fiff/meas_info.py
mne/_fiff/open.py
mne/_fiff/pick.py
mne/_fiff/proc_history.py
mne/_fiff/proj.py
mne/_fiff/reference.py
mne/_fiff/tag.py
mne/_fiff/tree.py
mne/_fiff/utils.py
mne/_fiff/what.py
mne/_fiff/write.py
mne/_fiff/tests/__init__.py
mne/_fiff/tests/test_compensator.py
mne/_fiff/tests/test_constants.py
mne/_fiff/tests/test_meas_info.py
mne/_fiff/tests/test_pick.py
mne/_fiff/tests/test_proc_history.py
mne/_fiff/tests/test_reference.py
mne/_fiff/tests/test_show_fiff.py
mne/_fiff/tests/test_utils.py
mne/_fiff/tests/test_what.py
mne/_fiff/tests/test_write.py
mne/beamformer/__init__.py
mne/beamformer/__init__.pyi
mne/beamformer/_compute_beamformer.py
mne/beamformer/_dics.py
mne/beamformer/_lcmv.py
mne/beamformer/_rap_music.py
mne/beamformer/resolution_matrix.py
mne/beamformer/tests/__init__.py
mne/beamformer/tests/test_dics.py
mne/beamformer/tests/test_external.py
mne/beamformer/tests/test_lcmv.py
mne/beamformer/tests/test_rap_music.py
mne/beamformer/tests/test_resolution_matrix.py
mne/channels/__init__.py
mne/channels/__init__.pyi
mne/channels/_dig_montage_utils.py
mne/channels/_standard_montage_utils.py
mne/channels/channels.py
mne/channels/interpolation.py
mne/channels/layout.py
mne/channels/montage.py
mne/channels/data/layouts/CTF-275.lout
mne/channels/data/layouts/CTF151.lay
mne/channels/data/layouts/CTF275.lay
mne/channels/data/layouts/EEG1005.lay
mne-1.6.1.dist-info/LICENSE.txt
mne-1.6.1.dist-info/METADATA
mne-1.6.1.dist-info/WHEEL
mne-1.6.1.dist-info/entry_points.txt
mne-1.6.1.dist-info/top_level.txt
mne-1.6.1.dist-info/RECORD
