Metadata-Version: 2.1
Name: mne
Version: 1.6.1
Summary: MNE-Python project for MEG and EEG data analysis.
Author-email: Alexandre Gramfort <alexandre.gramfort@inria.fr>
Maintainer-email: Dan McCloy <dan@mccloy.info>
License: BSD-3-Clause
Project-URL: Homepage, https://mne.tools/
Project-URL: Download, https://pypi.org/project/mne/#files
Project-URL: Bug Tracker, https://github.com/mne-tools/mne-python/issues/
Project-URL: Documentation, https://mne.tools/
Project-URL: Forum, https://mne.discourse.group/
Project-URL: Source Code, https://github.com/mne-tools/mne-python/
Keywords: neuroscience,neuroimaging,MEG,EEG,ECoG,fNIRS,brain
Classifier: Intended Audience :: Science/Research
Classifier: Intended Audience :: Developers
Classifier: License :: OSI Approved
Classifier: Programming Language :: Python
Classifier: Topic :: Software Development
Classifier: Topic :: Scientific/Engineering
Classifier: Operating System :: Microsoft :: Windows
Classifier: Operating System :: POSIX
Classifier: Operating System :: Unix
Classifier: Operating System :: MacOS
Classifier: Programming Language :: Python :: 3
Requires-Python: >=3.8
License-File: LICENSE.txt
Requires-Dist: numpy>=1.21.2
Requires-Dist: scipy>=1.7.1
Requires-Dist: matplotlib>=3.5.0
Requires-Dist: tqdm
Requires-Dist: pooch>=1.5
Requires-Dist: decorator
Requires-Dist: packaging
Requires-Dist: jinja2
Requires-Dist: importlib_resources>=5.10.2; python_version < "3.9"
Requires-Dist: lazy_loader>=0.3
Provides-Extra: data
Provides-Extra: hdf5
Requires-Dist: h5io; extra == "hdf5"
Requires-Dist: pymatreader; extra == "hdf5"
Provides-Extra: full
Requires-Dist: mne[hdf5]; extra == "full"
Requires-Dist: qtpy; extra == "full"
Requires-Dist: PyQt6!=6.6.1; extra == "full"
Requires-Dist: PyQt6-Qt6!=6.6.1; extra == "full"
Requires-Dist: pyobjc-framework-Cocoa>=5.2.0; platform_system == "Darwin" and extra == "full"
Requires-Dist: sip; extra == "full"
Requires-Dist: scikit-learn; extra == "full"
Requires-Dist: nibabel; extra == "full"
Requires-Dist: openmeeg>=2.5.5; extra == "full"
Requires-Dist: numba; extra == "full"
Requires-Dist: h5py; extra == "full"
Requires-Dist: pandas; extra == "full"
Requires-Dist: numexpr; extra == "full"
Requires-Dist: jupyter; extra == "full"
Requires-Dist: python-picard; extra == "full"
Requires-Dist: statsmodels; extra == "full"
Requires-Dist: joblib; extra == "full"
Requires-Dist: psutil; extra == "full"
Requires-Dist: dipy; extra == "full"
Requires-Dist: vtk; extra == "full"
Requires-Dist: nilearn; extra == "full"
Requires-Dist: xlrd; extra == "full"
Requires-Dist: imageio>=2.6.1; extra == "full"
Requires-Dist: imageio-ffmpeg>=0.4.1; extra == "full"
Requires-Dist: traitlets; extra == "full"
Requires-Dist: pyvista!=0.35.2,!=0.38.0,!=0.38.1,!=0.38.2,!=0.38.3,!=0.38.4,!=0.38.5,!=0.38.6,!=0.42.0,>=0.32; extra == "full"
Requires-Dist: pyvistaqt>=0.4; extra == "full"
Requires-Dist: mffpy>=0.5.7; extra == "full"
Requires-Dist: ipywidgets; extra == "full"
Requires-Dist: ipympl; extra == "full"
Requires-Dist: ipyevents; extra == "full"
Requires-Dist: trame; extra == "full"
Requires-Dist: trame-vtk; extra == "full"
Requires-Dist: trame-vuetify; extra == "full"
Requires-Dist: mne-qt-browser; extra == "full"
Requires-Dist: darkdetect; extra == "full"
Requires-Dist: qdarkstyle; extra == "full"
Requires-Dist: threadpoolctl; extra == "full"
Requires-Dist: eeglabio; extra == "full"
Requires-Dist: EDFlib-Python; extra == "full"
Requires-Dist: pybv; extra == "full"
Requires-Dist: snirf; extra == "full"
Requires-Dist: defusedxml; extra == "full"
Provides-Extra: test
Requires-Dist: pytest; extra == "test"
Requires-Dist: pytest-cov; extra == "test"
Requires-Dist: pytest-timeout; extra == "test"
Requires-Dist: pytest-harvest; extra == "test"
Requires-Dist: pytest-qt; extra == "test"
Requires-Dist: ruff; extra == "test"
Requires-Dist: numpydoc; extra == "test"
Requires-Dist: codespell; extra == "test"
Requires-Dist: check-manifest; extra == "test"
Requires-Dist: tomli; python_version < "3.11" and extra == "test"
Requires-Dist: twine; extra == "test"
Requires-Dist: wheel; extra == "test"
Requires-Dist: pre-commit; extra == "test"
Requires-Dist: black; extra == "test"
Provides-Extra: test-extra
Requires-Dist: mne[test]; extra == "test-extra"
Requires-Dist: nitime; extra == "test-extra"
Requires-Dist: nbclient; extra == "test-extra"
Requires-Dist: sphinx-gallery; extra == "test-extra"
Requires-Dist: eeglabio; extra == "test-extra"
Requires-Dist: EDFlib-Python; extra == "test-extra"
Requires-Dist: pybv; extra == "test-extra"
Requires-Dist: imageio>=2.6.1; extra == "test-extra"
Requires-Dist: imageio-ffmpeg>=0.4.1; extra == "test-extra"
Requires-Dist: snirf; extra == "test-extra"
Provides-Extra: doc
Requires-Dist: sphinx>=6; extra == "doc"
Requires-Dist: numpydoc; extra == "doc"
Requires-Dist: pydata_sphinx_theme==0.13.3; extra == "doc"
Requires-Dist: sphinx-gallery; extra == "doc"
Requires-Dist: sphinxcontrib-bibtex>=2.5; extra == "doc"
Requires-Dist: memory_profiler; extra == "doc"
Requires-Dist: neo; extra == "doc"
Requires-Dist: seaborn!=0.11.2; extra == "doc"
Requires-Dist: sphinx_copybutton; extra == "doc"
Requires-Dist: sphinx-design; extra == "doc"
Requires-Dist: sphinxcontrib-youtube; extra == "doc"
Requires-Dist: mne-bids; extra == "doc"
Requires-Dist: pyxdf; extra == "doc"
Requires-Dist: mne-connectivity; extra == "doc"
Requires-Dist: mne-gui-addons; extra == "doc"
Requires-Dist: pygments>=2.13; extra == "doc"
Requires-Dist: pytest; extra == "doc"
Requires-Dist: graphviz; extra == "doc"
Requires-Dist: pyzmq!=24.0.0; extra == "doc"
Requires-Dist: ipython!=8.7.0; extra == "doc"
Requires-Dist: selenium; extra == "doc"
Provides-Extra: dev
Requires-Dist: mne[doc,test]; extra == "dev"
